ged2doc/__init__.py
ged2doc/ancestor_tree.py
ged2doc/ancestor_tree_emf.py
ged2doc/ancestor_tree_svg.py
ged2doc/cli.py
ged2doc/dumbemf.py
ged2doc/dumbsvg.py
ged2doc/events.py
ged2doc/html_writer.py
ged2doc/i18n.py
ged2doc/input.py
ged2doc/name.py
ged2doc/odt_writer.py
ged2doc/py.typed
ged2doc/size.py
ged2doc/textbox.py
ged2doc/utils.py
ged2doc/writer.py
ged2doc/data/lang/cz/ged2doc.mo
ged2doc/data/lang/en/ged2doc.mo
ged2doc/data/lang/pl/ged2doc.mo
ged2doc/data/lang/ru/ged2doc.mo
ged2doc/data/styles/default
ged2doc-0.6.1.dist-info/licenses/LICENSE
ged2doc-0.6.1.dist-info/METADATA
ged2doc-0.6.1.dist-info/WHEEL
ged2doc-0.6.1.dist-info/entry_points.txt
ged2doc-0.6.1.dist-info/top_level.txt
ged2doc-0.6.1.dist-info/RECORD
