Metadata-Version: 2.4
Name: ged2doc
Version: 0.6.1
Summary: Tools for converting GEDCOM data into document formats.
Author-email: Andy Salnikov <ged4py@py-dev.com>
Maintainer-email: Andy Salnikov <ged4py@py-dev.com>
License: MIT license
Project-URL: bugs, https://github.com/andy-z/ged2doc/issues
Project-URL: homepage, https://ged2doc.readthedocs.io/
Classifier: Development Status :: 4 - Beta
Classifier: Intended Audience :: Developers
Classifier: License :: OSI Approved :: MIT License
Classifier: Operating System :: OS Independent
Classifier: Programming Language :: Python :: 3
Classifier: Programming Language :: Python :: 3 :: Only
Classifier: Programming Language :: Python :: 3.11
Classifier: Programming Language :: Python :: 3.12
Classifier: Programming Language :: Python :: 3.13
Classifier: Topic :: Sociology :: Genealogy
Requires-Python: >=3.11.0
License-File: LICENSE
Requires-Dist: ged4py
Requires-Dist: pillow
Requires-Dist: odfpy
Provides-Extra: dev
Requires-Dist: coverage; extra == "dev"
Requires-Dist: mypy; extra == "dev"
Requires-Dist: pytest; extra == "dev"
Requires-Dist: ruff; extra == "dev"
Dynamic: license-file
